pynomial/__init__.py
pynomial/pynomial_configuration.py
pynomial/azure/__init__.py
pynomial/azure/access_manager.py
pynomial/data_source/__init__.py
pynomial/data_source/connection.py
pynomial/data_source/odbc_connection.py
pynomial-1.0.4.dist-info/LICENSE
pynomial-1.0.4.dist-info/METADATA
pynomial-1.0.4.dist-info/WHEEL
pynomial-1.0.4.dist-info/top_level.txt
pynomial-1.0.4.dist-info/RECORD
