Metadata-Version: 2.1
Name: pynomial
Version: 1.0.4
Summary: pynomial
Home-page: https://github.com/Silver-Creek/pynomial.git
Author: Silver Creek
Author-email: austin.mcleod@silvercreeksoftware.com
License: UNKNOWN
Download-URL: https://github.com/Silver-Creek/pynomial/archive/v0.1.tar.gz
Platform: UNKNOWN
Classifier: Programming Language :: Python :: 3
Classifier: License :: OSI Approved :: MIT License
Classifier: Operating System :: OS Independent
Requires-Python: >=3.5
Requires-Dist: azure (==4.0.0)
Requires-Dist: azure-keyvault (==4.0.0)
Requires-Dist: azure-keyvault-secrets
Requires-Dist: azure-identity
Requires-Dist: pyodbc
